omio/__init__.py
omio/omio.py
omio_microscopy-0.2.0.dist-info/licenses/LICENSE
omio_microscopy-0.2.0.dist-info/WHEEL
omio_microscopy-0.2.0.dist-info/METADATA
omio_microscopy-0.2.0.dist-info/RECORD
