Metadata-Version: 2.4
Name: omio-microscopy
Version: 0.2.0
Summary: OMIO: Open Microscopy Image I/O
Author: Fabrizio Musacchio
Author-email: Fabrizio Musacchio <fabrizio.musacchio@posteo.de>
Maintainer-email: Fabrizio Musacchio <fabrizio.musacchio@posteo.de>
Requires-Python: >=3.12
License-Expression: GPL-3.0-or-later
License-File: LICENSE
Requires-Dist: numpy
Requires-Dist: tifffile
Requires-Dist: imagecodecs
Requires-Dist: czifile
Requires-Dist: zarr
Requires-Dist: dask[array]
Requires-Dist: numcodecs
Requires-Dist: tqdm
Requires-Dist: pyyaml
Requires-Dist: napari
Requires-Dist: pytest ; extra == "dev"
Requires-Dist: pytest-cov ; extra == "dev"
Project-URL: Documentation, https://github.com/FabrizioMusacchio/omio#readme
Project-URL: Homepage, https://github.com/FabrizioMusacchio/omio
Project-URL: Source, https://github.com/FabrizioMusacchio/omio
Project-URL: Tracker, https://github.com/FabrizioMusacchio/omio/issues
Provides-Extra: dev
